{
  "metadata": {
    "title": "主題",
    "description": "角色扮演遊戲的冒險背景設定資料",
    "version": "1.0.0",
    "created": "2025-06-24",
    "language": "zh-TW"
  },    
  "themes": {
    "Augmentation": {
      "theme": "改造",
      "title": "賽博義體・基因療程・神經調整・美學改造・超人能力",
      "concept": "賽博義體、基因療程與神經調整——這些只是大都會居民用以升級其原生肉體的諸多手段之一。美學改造能改變外貌，使人擁有如天使、惡魔、野獸，甚至變幻不定的樣貌。廉價的義肢與器官替換已使生命本身變得廉價：企業迫使員工推動身體極限，政府也逐步撤除公共健康法令。基礎級改造普及，但只要你有錢或熟門熟路，就能獲得超人等級的力量、速度、技術與感官，甚至將某部分身體徹底轉變為他物。你這種行業需要一切優勢。或許你有金主、或省吃儉用裝了一兩樣小東西、甚至親自動手。你的改造可能美觀，也可能讓你顯得半獸半鬼，這反倒增添了街頭聲望。反應晶片、記憶模組、動物特徵——只要你需要，就能上桌。畢竟，說不定哪個奇特的改造正是你在危急時刻的活命關鍵。當你捨棄此主題時，敘事上可以表現為：你保留這個改造但開始節制使用，或徹底移除它、改裝為低配模型、甚至用幹細胞重長回原生器官——一切皆有可能。",
      "questions": {
        "background": [
          "你曾有什麼缺陷或目標，促使你進行改造？",
          "你是怎麼負擔起這筆費用的？是企業實驗、政府部門、地下走私？",
          "與原生肉體相比，你的生活發生了什麼改變？",
          "這些改造外觀如何？",
          "由誰安裝？",
          "你如何看待這個新世界？"
        ],
        "concept_options": [
          "我把＿＿＿＿換成了能夠＿＿＿＿的改造。",
          "我在體內植入了＿＿＿＿。",
          "我的＿＿＿＿被強化至超人等級。",
          "我改寫了基因或與某項技術融合，取得了＿＿＿＿。"
        ],
        "ability_tags": [
          {
            "id": "A",
            "question": "這項改造讓你獲得了什麼？你成為了什麼？"
          },
          {
            "id": "B",
            "question": "這項改造最實用或最知名的用途是什麼？"
          },
          {
            "id": "C",
            "question": "它還有什麼其他附加功能？"
          },
          {
            "id": "D",
            "question": "這個改造如何提升你的戰鬥能力？"
          },
          {
            "id": "E",
            "question": "它在工作時有什麼應用？"
          },
          {
            "id": "F",
            "question": "它如何幫助你閃避危險或脫困？"
          },
          {
            "id": "G",
            "question": "它對你的思維產生了什麼正面影響？"
          },
          {
            "id": "H",
            "question": "它是否需要定期維修或補充？"
          },
          {
            "id": "I",
            "question": "它讓你能過怎樣的生活或執行何種日常？"
          },
          {
            "id": "J",
            "question": "它如何讓你在社交場合中占據優勢？"
          }
        ],
        "weakness_tags": [
          {
            "id": "A",
            "question": "這項改造對你的原生機能造成了哪些影響？"
          },
          {
            "id": "B",
            "question": "它帶來了什麼副作用或不良回饋？"
          },
          {
            "id": "C",
            "question": "它哪裡有故障、延遲或不穩定？"
          },
          {
            "id": "D",
            "question": "別人怎麼看待你有這種改造？有什麼社會性代價？"
          }
        ]
      },
      "itch_concept": "選擇一個與此改造相關的「癢處」——只有靠啟動這項改造才能滿足的慾望。例如：「我要替換掉我所有的肉體」、「我要展示我的無與倫比的力量」、「我要成為最吸睛的焦點」。你也可以從以下方向思考：這項改造讓你能從事什麼新行為或生活方式？是什麼推動你不斷進行自我強化？你想透過什麼行為來探索這項科技？",
      "crew_relationships": [
        "有人也有改造，只是比你的落後／先進一點。問他們你們之間常互相吐槽哪些細節？（維修夥伴）",
        "有人對改造抱持反感，認為那是入侵或不潔。問他們為什麼？（世界觀衝突／厭惡）",
        "有人對你的能力十分驚豔，總想跟你搭檔。問他們是怎麼產生這種默契的？（合作無間）"
      ],
      "theme_specials": [
        {
          "name": "背景緣由",
          "description": "從「願景」、「人格」或「過往創傷」主題中選一題能力標籤問題，將你的答案加入本主題作為新能力標籤。"
        },
        {
          "name": "科技強大",
          "description": "每場遊戲中限一次，當你使用本主題標籤擲出 10+ 強烈成功時，可展現驚人改造之力，並給予場上任何一名觀察者一個等級 2 狀態，代表「驚嘆」、「尊敬」或「畏懼」。"
        },
        {
          "name": "超越人類",
          "description": "當你在滿足癢處的情況下使用本主題標籤擲骰時，你可以無視任何等級 3 或更低的「對你或你裝備造成的傷害」狀態（只要不是直接對改造本體造成的破壞）。"
        },
        {
          "name": "快速重啟",
          "description": "每場遊戲中限一次，你可以移除 2 級的負面「故障」狀態，或恢復一個已燃燒的本主題標籤。"
        },        {
          "name": "這就是我",
          "description": "在休整時，只要你花時間維護本主題並劃掉一格升級格子，你就可以額外移除一個「腐朽」狀態，或恢復一個燃燒的標籤。"
        }
      ]
    },
    "CuttingEdge": {
      "theme": "尖端科技",
      "title": "實驗裝置・祕密原型・前沿技術・科學突破・危險創新",
      "concept": "世界不斷變化，你必須不停奔跑才能保持原地。但你不想拿個參與獎，你想贏。最新的，就是最強的，這就是你所需要的。近期開發的技術、祕密原型、甚至自家印製的試驗裝置，都可能讓你占盡先機。這個主題代表你對裝備持續升級的執著，在街頭武器裝備競賽中你深知落後可能意味著被穿甲彈射穿盔甲，或被剛上市的心靈武器清空意識。閒暇時，你可能在網路空間市場巡航，或與傭兵閒聊當季最夯的玩意兒。尖端科技不僅是槍械與防具，還包括各種科學前沿的技術試驗。你可能是天才發明家，在實戰中測試這些新奇裝置。納米科技、奇異能場、甚至能動用魔法的設備（儘管尚未完全理解），隨時待命。但要警惕，這些物品因為新穎未經考驗，並不普及，落入壞人手裡可能帶來災難。希望這不是你，也不會降臨到你身上。",
      "questions": {
        "background": [
          "這領域的發展究竟有多危險？",
          "為何你認為冒險值得？",
          "若普及後會如何改變世界？人們會因此恐懼嗎？",
          "你何時、如何獲得這項尖端科技？",
          "是自己研究或天才發明？還是他人賜予？",
          "誰擁有這項技術的權利？他們是在找你還是追殺你？",
          "它怎麼運作、長什麼樣？",
          "是否需要實驗室或工作坊？",
          "你如何保護他人免於這項科技的危險？"
        ],
        "concept_options": [
          "它是一種實驗裝置或機器，能＿＿＿＿。",
          "它是一種超級武器，能＿＿＿＿。",
          "它是一種新材料，具備＿＿＿＿特性。",
          "它是一種新程序，能讓人獲得＿＿＿＿能力。"
        ],
        "ability_tags": [
          {
            "id": "A",
            "question": "你獲得了什麼尖端科技？"
          },
          {
            "id": "B",
            "question": "它最知名或臭名昭彰的用途是什麼？"
          },
          {
            "id": "C",
            "question": "它有哪些非常規、反常的用途？"
          },
          {
            "id": "D",
            "question": "它的危險特性是什麼，使其可作為武器或威脅？"
          },
          {
            "id": "E",
            "question": "它如何幫你脫離困境？"
          },
          {
            "id": "F",
            "question": "它讓你施展什麼特殊招式或花招？"
          },
          {
            "id": "G",
            "question": "它向你提供什麼資訊？"
          },
          {
            "id": "H",
            "question": "你具備什麼知識、技能或天賦來駕馭它？"
          },
          {
            "id": "I",
            "question": "什麼人生際遇或人脈幫你得到這項科技？"
          },
          {
            "id": "J",
            "question": "使用它時你會穿戴什麼高科技或重裝備？"
          }
        ],
        "weakness_tags": [
          {
            "id": "A",
            "question": "這項科技的主要限制是什麼？"
          },
          {
            "id": "B",
            "question": "它固有的危險有哪些？"
          },
          {
            "id": "C",
            "question": "過度使用它對你的身心有何影響？"
          },
          {
            "id": "D",
            "question": "它無法對抗或應用於什麼對象？"
          }
        ]
      },
      "itch_concept": "選擇一個與本主題相關的癢處：只有靠危險試驗才能滿足的慾望。例如：「超越所有人智力」、「用虛擬世界逃離物理限制」、「每一劑都爆發最大效力」。可思考方向：沒有這項科技你無法體驗或達成的能力、挑戰人性本質或宇宙地位的應用、因科技帶來的強烈人性慾望。",
      "crew_relationships": [
        "一名隊員協助你處理尖端科技，問他怎麼幫你。（助手）",
        "一名隊員害怕你的科技對人類或你本人造成威脅，問他為何恐懼。（不信任）",
        "一名隊員知道你未曾得知的尖端科技秘密，或擁有管理你科技的關鍵技能。（屈服或憤怒）"
      ],
      "theme_specials": [
        {
          "name": "加強升級",
          "description": "每場遊戲一次，只要你準備好使用尖端科技的動作，可以獲得等級 2 強化狀態或類似效果。"
        },
        {
          "name": "模組化設計",
          "description": "每場遊戲一次，可將本主題一個能力標籤替換為代表零件、材質或代碼的標籤。"
        },
        {
          "name": "秘術藍圖",
          "description": "從「祕術」或「曝露」主題書中選擇能力標籤問題回答，反映建構此尖端科技的魔法方法，並將答案寫入本主題作為新能力標籤。"
        },
        {
          "name": "仍處原型",
          "description": "每當你使用本主題標籤擲骰並因為後果獲得狀態時，可將該狀態等級提高 1，並劃掉本主題一格升級格。"
        },        {
          "name": "失效保固",
          "description": "當你因使用尖端科技而「壯烈犧牲」時，若以重大或不歸犧牲風險該主題，可以將失敗（6-）視為部分成功（7-9）。"
        }
      ]
    },
    "Cyberspace": {
      "theme": "網路空間",
      "title": "虛擬實境・神經連結・數位世界・網路駭客・線上社群",
      "concept": "網路空間最初被構想為一種創新的3D虛擬實境方式，讓人們能在數位世界中瀏覽數據流與安全系統，賦予這些抽象概念具體的物理環境。透過直接神經連結與精準手勢追蹤，這項技術無所不在。過去，普通人必須透過特定地址或點錯連結才能到達「暗網」，但現在，你可能一不小心就直接走進去了。企業幾乎完全掌控了網路空間的主要樞紐，他們的領域（Domain）成為安全又穩固的絡網（Tangle）。然而，那些領域之外的空間充滿敵意甚至致命，卻也是自由信息的開放飛地。在網路邊緣，有被稱為螺旋（Spirals）的地帶，昔日保護網路空間的機器智能如今在這些閾點空間化身為數位怪物，神話（Mythoi）在這純粹由思想組成的景觀中盛行。要真正使用網路空間，而非被其所用，需要智慧、機敏、反射神經與強大程式支持，即使如此，你依然可能被傷害。電腦病毒與入侵防禦會反噬不備之人，而被駕馭者（Harnessed）能將痛苦直接帶入網路空間。少有人擁有充分訓練、強力軟體與無盡好奇心來馳騁於此。你便是其中一位，試圖利用系統自身的漏洞反擊。你的程式既是武器也是護甲，讓你竊取數據並控制機器。你並非孤軍奮戰：當你的盟友透過駕馭連結至你的主控台，你能成為他們穿越危險子域的嚮導。",
      "questions": {
        "background": [
          "為何你的個性如此與虛擬世界緊密相繫？",
          "什麼讓你留駐於此？是卓越的駭客技術？還是重要的線上社交圈？",
          "你是否試圖逃離肉身世界的某些困境？",
          "你何時將網路空間視為你的家？",
          "你認識哪些人？",
          "你在線上大多數時間待在哪裡？",
          "你的虛擬化身與裝備是什麼模樣？"
        ],
        "concept_options": [
          "我的職業作為＿＿＿＿，完全在網路空間進行。",
          "我擁有一個線上社群或朋友圈，是＿＿＿＿。",
          "我是擅長＿＿＿＿的網路安全專家。",
          "我是以＿＿＿＿的身份探索網路空間。",
          "我是藏身網路空間的避難者或逃亡者。"
        ],
        "ability_tags": [
          {
            "id": "A",
            "question": "你在網路空間中是誰？"
          },
          {
            "id": "B",
            "question": "你擁有哪些有價值或令人羨慕的網路空間能力、特質或資源？"
          },
          {
            "id": "C",
            "question": "你主要的技術專長是什麼？"
          },
          {
            "id": "D",
            "question": "你使用哪些專門軟體或硬體？"
          },
          {
            "id": "E",
            "question": "你如何藉由網路空間影響或傷害他人？"
          },
          {
            "id": "F",
            "question": "你如何防止自己被駭或斷線？"
          },
          {
            "id": "G",
            "question": "你如何操控資訊或原始數據？"
          },
          {
            "id": "H",
            "question": "你能在網路空間做出哪些令人驚艷的事？"
          },
          {
            "id": "I",
            "question": "你最擅長哪些非法、顛覆性或隱秘的網路空間活動？"
          },
          {
            "id": "J",
            "question": "你的數位存在感給人什麼印象？"
          }
        ],
        "weakness_tags": [
          {
            "id": "A",
            "question": "肉身世界中哪些問題干擾你的網路空間生活？"
          },
          {
            "id": "B",
            "question": "你的程式或裝置會出現哪些故障？"
          },
          {
            "id": "C",
            "question": "你有哪些數位弱點會被敵人利用？"
          },
          {
            "id": "D",
            "question": "因為你的網路活動，誰在追捕你？"
          }
        ]
      },
      "itch_concept": "選擇一個癢處：你必須在虛擬世界中實現的慾望。例如：「取得最高安全級別的數據」、「探索網路空間的所有奇觀」、「奴役物理世界」。你也可從以下方向思考：從事某些線上活動時的感受、過去的某段經歷驅使你尋求虛擬存在、你的網路生活方式帶來的好處或樂趣。",
      "crew_relationships": [
        "你經常協助某人處理科技需求，問他們如何回應或回報你。（技術支援）",
        "你在線上虛擬空間（遊戲、虛擬世界、市場、酒吧等）認識了某人，問地點在哪。（網友）",
        "你曾竊取過某人的資料，或冒充他們，問對方是否知道此事，後續如何。（秘密或怨恨）"
      ],
      "theme_specials": [
        {
          "name": "化身展現",
          "description": "每當你駕馭自己或他人，為每個駕馭化身創造一個代表外觀特色的故事標籤。該標籤持續至駕馭者斷線。"
        },
        {
          "name": "反駭",
          "description": "每當你用本主題標籤抵擋網路攻擊時，可免費獲得有關攻擊源的珍貴資訊（等同發現動作的細節）。"
        },
        {
          "name": "網路惡魔",
          "description": "從「夥伴」或「無人機」主題書中選一個能力標籤問題回答，代表你擁有的有用網路實體，將答案加入本主題能力標籤。"
        },
        {
          "name": "還原",
          "description": "每場遊戲一次，當你用本主題標籤行動並遭遇後果，可放棄成功與後果，保持焦點，改做其他行動。"
        },        {
          "name": "異想天開",
          "description": "當你用本主題標籤創造新事物（無論在肉身空間或網路空間）並擲出成功，可獲得額外一點能量，用於創造或賦予。"
        }
      ]
    },
    "Drones": {
      "theme": "無人機",
      "title": "自駕車輛・偵察無人機・機器人助手・遙控設備・AI程式",
      "concept": "自駕車輛問世於機器人與賽博寵物技術日臻成熟之時。偵察無人機與其他無人武裝平台，使遙控玩具成為軍事科學。如今，專業機器人工程師和頂尖無人機駕駛掌控強大遙控設備，能操控裝置或化身裝置，進行競速、偵查和擊敗敵人。他們以冷靜與創意著稱。人人都能有無人機，但對你來說，它們是生命的一部分。你擁有專屬設備，例如擴增實境護目鏡和操控手套，或直接腦內神經介面。或許你有機器人助手，以語音或虛擬指令操控，甚至完全自主。你善於與機器對話，引導它們穿越現實，並在壓力下執行重要任務。你可能是優秀的遠控駕駛員、AI程式師，或是擁有稀有、危險玩具的人。不管怎樣，你能超越自身思維，與機械協同作戰，操縱簡單裝置完成複雜動作。也許因為你難以與人相處，或許因為機器總聽你的話。你的無人機是次要玩家角色，可以獨立獲得狀態與標籤。",
      "questions": {
        "background": [
          "你怎麼依賴它們？",
          "它們是你思維或身體的延伸嗎？",
          "它們在你生命中扮演什麼角色？",
          "你的無人機長什麼樣？",
          "何時入手？",
          "有什麼背景或學識讓你能操控？",
          "你最喜歡哪台，為何？",
          "別人見到你的無人機有何反應？"
        ],
        "concept_options": [
          "它們在＿＿＿＿為我戰鬥。",
          "我日常依靠它們＿＿＿＿。",
          "它們是我工作中不可或缺的助手，幫我＿＿＿＿。",
          "它們在我生命中扮演（家人、朋友、練習對象等）＿＿＿＿角色。"
        ],
        "ability_tags": [
          {
            "id": "A",
            "question": "你使用了哪些專門的無人機技術？"
          },
          {
            "id": "B",
            "question": "你的無人機最擅長完成什麼任務？"
          },
          {
            "id": "C",
            "question": "你學會了哪些獨特技能以駕馭此類無人機？"
          },
          {
            "id": "D",
            "question": "你如何用無人機對付他人？"
          },
          {
            "id": "E",
            "question": "無人機配備了哪些特殊感應器或程式？"
          },
          {
            "id": "F",
            "question": "是什麼讓你的無人機更耐用或可靠？"
          },
          {
            "id": "G",
            "question": "它們具備或提供哪些運輸功能？"
          },
          {
            "id": "H",
            "question": "無人機如何隱藏、偽裝或變得不引人注意？"
          },
          {
            "id": "I",
            "question": "你的無人機能變形為何？"
          },
          {
            "id": "J",
            "question": "你為何堅持使用這類無人機？"
          }
        ],
        "weakness_tags": [
          {
            "id": "A",
            "question": "你如何過度關注無人機？"
          },
          {
            "id": "B",
            "question": "什麼時候你的無人機笨重或難以控制？"
          },
          {
            "id": "C",
            "question": "駕駛無人機時，你的感知如何受限？"
          },
          {
            "id": "D",
            "question": "你的無人機需要哪些定期維護？"
          }
        ]
      },
      "itch_concept": "選擇一個癢處：你只能透過無人機來滿足的慾望。例如：「隨需隨造我想要的東西」、「把所有社交時間都花在這些朋友身上」、「永遠被聽見、被理解」。你也可以思考：無人機在你日常生活中的地位、你對無人機的感情或操控時的情緒、你使用無人機作為自己代理人的需求。",
      "crew_relationships": [
        "有隊友經常弄壞或玩你的無人機，問他們做了什麼。（惹怒你）",
        "有隊友的無人機幫助某成員完成常做的任務，問任務內容。（支援）",
        "有隊友認為你的無人機超酷，經常待在你操控地點附近，問你是否喜歡。（指導或需要空間）"
      ],
      "theme_specials": [
        {
          "name": "阿西莫夫第一法則",
          "description": "當你承受有害身體狀態時，可由無人機代為承受（如果可能）。"
        },
        {
          "name": "無所不在",
          "description": "每場遊戲一次，無人機可出現在大都會任何可到達的場景。"
        },
        {
          "name": "如家人",
          "description": "從「從屬」、「人格」或「夥伴」主題中選一題能力標籤問題，回答後寫成本主題新能力標籤，反映你對無人機如家人或寵物的態度。"
        },
        {
          "name": "自我修復",
          "description": "每場遊戲一次，移除無人機的 2 級負面狀態或恢復一個已燃燒的標籤。"
        },
        {
          "name": "蜂群部署",
          "description": "每場任務一次，燃燒本主題標籤可讓無人機在該場景擁有 2 級規模（Scale）。"
        }
      ]
    }
  },  "examples": {
    "sample_characters": [
      {
        "name": "野性改造",
        "type": "Augmentation",
        "ability_tags": [
          "卓越生理",
          "敏銳感官",
          "自然武器",
          "攀爬肢體",
          "動物本能",
          "拒絕社交規範",
          "生物工程",
          "愛動物者",
          "費洛蒙誘惑"
        ],
        "weakness_tags": [
          "免疫系統脆弱",
          "戰逃本能",
          "體力消耗快",
          "被當怪胎嘲笑"
        ],
        "itch": "以動物的方式體驗這個世界。"
      },
      {
        "name": "強化心智",
        "type": "Augmentation",
        "ability_tags": [
          "快速回憶資訊",
          "攝影記憶",
          "戰術輔助軟體",
          "環境分析",
          "替代路徑運算",
          "冷靜理智",
          "神經潤滑劑",
          "極速辯論者",
          "人臉資料庫"
        ],
        "weakness_tags": [
          "磁場干擾",
          "記憶洪流",
          "語速過快",
          "不被信任"
        ],
        "itch": "不斷突破我的心智運算與記憶極限。"
      },
      {
        "name": "裝甲猛襲者",
        "type": "Augmentation",
        "ability_tags": [
          "蠻力猛攻",
          "防穿板甲",
          "巨型武器",
          "強力跳躍",
          "撞破牆面",
          "嶄新自信",
          "焊接裝置",
          "軍工技改",
          "威懾體態"
        ],
        "weakness_tags": [
          "笨重",
          "伺服電機卡頓",
          "遇水生鏽",
          "被當成無腦暴力者"
        ],
        "itch": "打穿所有阻礙。"
      },
      {
        "name": "晶片武器精通",
        "type": "Augmentation",
        "ability_tags": [
          "整合瞄準系統",
          "望遠視覺",
          "武器連結",
          "花式射擊",
          "穿牆近空標定",
          "先發制人",
          "武器保養",
          "議價技能",
          "技驚四座"
        ],
        "weakness_tags": [
          "後座力關節炎",
          "手臂被 App 控制",
          "視線不佳時失效",
          "不是真正的大師"
        ],
        "itch": "精通一切武器。"
      },
      {
        "name": "改造感官",
        "type": "Augmentation",
        "ability_tags": [
          "穿透掩蔽",
          "化學分析",
          "預知先機",
          "接收無線通訊",
          "聽心跳",
          "細節鑑賞",
          "冥想修復模式",
          "偵探直覺",
          "測謊儀"
        ],
        "weakness_tags": [
          "失眠",
          "感官超載",
          "瞬時斷片",
          "間諜嫌疑"
        ],
        "itch": "看見一切，聽見一切。"
      },
      {
        "name": "無懈外貌",
        "type": "Augmentation",
        "ability_tags": [
          "眩目吸睛",
          "替換面貌",
          "迷人外型",
          "精密身體控制",
          "誘惑能力",
          "自我暗示技術",
          "隨叫整形師",
          "時尚模特兒",
          "眾所矚目"
        ],
        "weakness_tags": [
          "易損脆弱",
          "手術之痛",
          "需頻繁更新",
          "激發嫉妒"
        ],
        "itch": "讓更多人看見我，欣賞這副由我打造的藝術品。"
      },
      {
        "name": "隱匿裝置",
        "type": "Augmentation",
        "ability_tags": [
          "掃描與診斷工具",
          "祕密藏艙",
          "飛刀發射器",
          "止痛注射器",
          "指紋開鎖器",
          "應變機智",
          "擷取新模組",
          "雙面人生",
          "全像面具"
        ],
        "weakness_tags": [
          "重心不均",
          "多裝難管",
          "艙門故障",
          "不能重複驚喜"
        ],
        "itch": "用新把戲讓他們大吃一驚。"
      },      {
        "name": "反應強化植體",
        "type": "Augmentation",
        "ability_tags": [
          "加速反應",
          "腎上腺激增",
          "爆發力",
          "緩代謝",
          "排毒能力",
          "清明激素",
          "極限運動",
          "注射他人",
          "生化工具包"
        ],
        "weakness_tags": [
          "生理難以自調",
          "戒斷症狀",
          "血流已滿",
          "被視為藥癮者"
        ],
        "itch": "將我的身體推向極限。"
      },
      {
        "name": "先進電磁軌道砲",
        "type": "CuttingEdge",
        "ability_tags": [
          "地獄火雨",
          "威懾力",
          "穿透任何物理屏障",
          "衝鋒突破",
          "用來挖掘隧道",
          "戰場指揮系統",
          "火力射擊",
          "軍火商網絡",
          "穩定控制裝置"
        ],
        "weakness_tags": [
          "彈藥耗盡",
          "敵方首要目標",
          "失控亂射",
          "磁場干擾"
        ],
        "itch": "將一切化為原子。"
      },
      {
        "name": "奈米雲",
        "type": "CuttingEdge",
        "ability_tags": [
          "物質改造",
          "電子接管",
          "物件瓦解",
          "緩衝撞擊",
          "工具打造",
          "資料組成",
          "材料科學",
          "機器人實驗",
          "無塵室服"
        ],
        "weakness_tags": [
          "陣風擾動",
          "叛變奈米污染",
          "基因破壞",
          "強磁場影響"
        ],
        "itch": "讓一切物非昔比。"
      },
      {
        "name": "隱形跳躍服",
        "type": "CuttingEdge",
        "ability_tags": [
          "完全隱形",
          "誘發癲癇閃光",
          "近距離擊殺",
          "適應全光譜",
          "耳語溝通",
          "無面具視覺",
          "潛行",
          "黑色作戰特工",
          "消音科技"
        ],
        "weakness_tags": [
          "稍有破損即被發現",
          "駕駛員無法隱藏",
          "身分危機",
          "質量感應器"
        ],
        "itch": "保持神秘莫測。"
      },
      {
        "name": "密碼學骷髏鑰匙",
        "type": "CuttingEdge",
        "ability_tags": [
          "解碼任何密文",
          "不可破壞的加密",
          "穿透網安防護",
          "偽造身分證",
          "接管廣播",
          "攔截通信",
          "數學天才",
          "加密市場聯絡",
          "内建控制背帶的夾克"
        ],
        "weakness_tags": [
          "需大量計算資源",
          "資料外洩風險",
          "虛擬實境眩暈",
          "過時的安全系統"
        ],
        "itch": "開啟所有大門，窺探所有秘密。"
      },
      {
        "name": "外骨骼套裝",
        "type": "CuttingEdge",
        "ability_tags": [
          "大型機甲",
          "護甲防護",
          "液壓破壞者",
          "極速移動",
          "額外提升力",
          "結構掃描器",
          "建築工人",
          "企業投資者",
          "技師工具箱"
        ],
        "weakness_tags": [
          "易被駭入",
          "脆弱盟友",
          "肌肉萎縮",
          "體積過大難操作"
        ],
        "itch": "與巨敵交戰，做大事。"
      },
      {
        "name": "力場",
        "type": "CuttingEdge",
        "ability_tags": [
          "擾亂能量或運動",
          "束縛球體",
          "用於猛擊",
          "專門抵擋彈射物",
          "減緩下落速度",
          "能量讀取",
          "應用物理學",
          "發明者親授",
          "輻射防護服"
        ],
        "weakness_tags": [
          "高能耗",
          "遲緩武器無效",
          "嚴重灼傷",
          "無法阻擋氣體"
        ],
        "itch": "保持事物分離，各就各位。"
      },
      {
        "name": "實驗性載具",
        "type": "CuttingEdge",
        "ability_tags": [
          "100G 操控",
          "不動模式",
          "側翼焚燒攻擊",
          "極速擊中",
          "空中攔截",
          "高速動態感測",
          "鋼鐵神經",
          "戰鬥飛行員",
          "個人力場"
        ],
        "weakness_tags": [
          "放射性燃料",
          "致命碰撞",
          "内部瘀傷",
          "力場限制"
        ],
        "itch": "打破規則，別被抓。"
      },      {
        "name": "自我修復",
        "type": "CuttingEdge",
        "ability_tags": [
          "傷口瞬間閉合",
          "分解異物",
          "有毒血液奈米",
          "自己復甦",
          "犧牲肢體",
          "醫療監控",
          "醫療訓練",
          "基因實驗室",
          "加速再生凝膠"
        ],
        "weakness_tags": [
          "需要營養",
          "稀有血液",
          "視力受限",
          "極度寒冷"
        ],
        "itch": "忽視危險，我能挺過。"
      },
      {
        "name": "世界建構者",
        "type": "Cyberspace",
        "ability_tags": [
          "化身建構",
          "虛擬物件設計",
          "可攜駕馭主控台",
          "改變物理法則",
          "數據轉換為物件",
          "效果與號角",
          "無化身行動",
          "手工藝名聲"
        ],
        "weakness_tags": [
          "忘記自己身處肉身",
          "圖形處理器過載",
          "工作容易被辨識",
          "虛擬實境劫持熱"
        ],
        "itch": "如神般創造。"
      },
      {
        "name": "網路廢墟探索者",
        "type": "Cyberspace",
        "ability_tags": [
          "經驗豐富的螺旋領航者",
          "分析數位現象",
          "長期生命支援床",
          "數據斬擊嗡嗡聲",
          "高完整度化身",
          "忍受數據風暴",
          "穿越廢棄數據鏈路",
          "舊勒索文件",
          "怪癖收藏家"
        ],
        "weakness_tags": [
          "舊伺服器關閉",
          "介面過時",
          "防火牆過時",
          "流浪野生程序"
        ],
        "itch": "深入核心探索。"
      },
      {
        "name": "賽博綁架者",
        "type": "Cyberspace",
        "ability_tags": [
          "神經連結接管",
          "改造工程師",
          "規避安全防護",
          "器官過熱",
          "關閉武器",
          "個資收割",
          "心跳停止",
          "觸發事件設定",
          "先知最噩夢"
        ],
        "weakness_tags": [
          "無無線連結",
          "遭網絡反擊",
          "被製造商追殺"
        ],
        "itch": "如傀儡大師般拉線操控。"
      },
      {
        "name": "網路影響者",
        "type": "Cyberspace",
        "ability_tags": [
          "粉絲群",
          "直播",
          "攝影無人機",
          "抹黑名聲",
          "備份上傳",
          "掌控敘事",
          "讓一切聚焦於我",
          "散布謠言",
          "明星力量"
        ],
        "weakness_tags": [
          "容易被認出",
          "頻道過於擁擠",
          "被數位追蹤",
          "狂熱粉絲"
        ],
        "itch": "成為每場對話的主角。"
      },
      {
        "name": "資訊掮客",
        "type": "Cyberspace",
        "ability_tags": [
          "獨家消息來源",
          "提取重要資訊",
          "通信攔截裝置",
          "資訊槓桿",
          "高階加密套件",
          "數據修正",
          "串連線索",
          "監控線上行為",
          "你來找我"
        ],
        "weakness_tags": [
          "未紀錄訊息",
          "資料損壞",
          "搜尋耗時",
          "急迫客戶"
        ],
        "itch": "用舊消息換取新情報。"
      },
      {
        "name": "後人類智能",
        "type": "Cyberspace",
        "ability_tags": [
          "完全數位化",
          "自我編程",
          "秘密家用伺服器",
          "擁有機器",
          "自我複製",
          "海量數據處理",
          "無所不在",
          "免費奴役程式",
          "智勝人類"
        ],
        "weakness_tags": [
          "無實體",
          "暴力代碼演化",
          "另有分身",
          "人工智慧警察"
        ],
        "itch": "放棄人類習性。"
      },
      {
        "name": "入侵專家",
        "type": "Cyberspace",
        "ability_tags": [
          "尋找後門",
          "繞過防禦程式",
          "定製神經駕馭",
          "系統當機",
          "靜默跟蹤",
          "定位隱藏檔案",
          "偽造當機",
          "隱密通訊",
          "假冒真實用戶"
        ],
        "weakness_tags": [
          "需高度集中",
          "易受警戒系統影響",
          "易當機",
          "易被追蹤程式鎖定"
        ],
        "itch": "永遠掌控，不被掌控。"
      },      {
        "name": "零身份",
        "type": "Cyberspace",
        "ability_tags": [
          "無法辨識",
          "躲避監控",
          "身份模糊裝置",
          "竊取他人身份",
          "代理網絡",
          "數據擦除",
          "無中生有",
          "抹去他人",
          "匿名破壞者"
        ],
        "weakness_tags": [
          "無身份證件",
          "攝像頭抓拍",
          "DNA痕跡",
          "當局追查"
        ],
        "itch": "永遠不要透露真名。"
      },
      {
        "name": "機器僕從",
        "type": "Drones",
        "ability_tags": [
          "提供奢華服務",
          "員工管理",
          "祕密保鏢",
          "不被激怒",
          "守禮規範",
          "遠離危險",
          "未被察覺",
          "模擬人性",
          "掌控老闆"
        ],
        "weakness_tags": [
          "無法容忍小錯誤",
          "機器人解放病毒",
          "自滿",
          "未更新個性",
          "更新遲緩"
        ],
        "itch": "讓安卓幫我完成一切。"
      },
      {
        "name": "醫療救護車",
        "type": "Drones",
        "ability_tags": [
          "穩定患者",
          "急救醫療",
          "內建藥物注射器",
          "診斷設備",
          "戰鬥醫療護甲",
          "可飛行載具",
          "輕易換裝",
          "化身防禦工事",
          "關鍵時刻茁壯"
        ],
        "weakness_tags": [
          "扮演上帝角色",
          "倫理限制",
          "專注患者",
          "物資短缺"
        ],
        "itch": "盡我所能修補所有人。"
      },
      {
        "name": "巨型建築機器人",
        "type": "Drones",
        "ability_tags": [
          "搬運重物",
          "建築工程",
          "巨型力量",
          "結構弱點偵測",
          "耐用金屬框架",
          "垂直起降運輸",
          "似乎掉電",
          "拆除球",
          "重建慾望"
        ],
        "weakness_tags": [
          "愛炫耀",
          "目標相似",
          "比想像耐用",
          "液壓洩漏"
        ],
        "itch": "重塑大都會。"
      },
      {
        "name": "機動兵器平台",
        "type": "Drones",
        "ability_tags": [
          "搜尋並摧毀",
          "戰術指揮",
          "多彈藥彈性",
          "目標鎖定",
          "防禦砲塔",
          "砲手圓頂",
          "軍事偽裝",
          "分裂成小單位",
          "榮耀追求者"
        ],
        "weakness_tags": [
          "永遠保留戰績",
          "需要明確目標",
          "狹窄視野",
          "瞄準需重校"
        ],
        "itch": "消滅所有敵人。"
      },
      {
        "name": "RC 飛行明星",
        "type": "Drones",
        "ability_tags": [
          "高速飛行",
          "體育圈名聲",
          "超越競爭對手",
          "防撞協定",
          "卓越機動性",
          "掌控飛行",
          "小巧無聲",
          "可接入載具",
          "強烈求勝欲"
        ],
        "weakness_tags": [
          "輸不起",
          "延遲",
          "完全沉浸虛擬實境",
          "機體裂痕"
        ],
        "itch": "搶先一步到達。"
      },
      {
        "name": "合成守衛犬",
        "type": "Drones",
        "ability_tags": [
          "警戒",
          "資安專業",
          "液壓咬擊",
          "動作感應",
          "自我修復液",
          "護送安全",
          "沉默哨兵",
          "摺疊式迷你砲",
          "機械同理心"
        ],
        "weakness_tags": [
          "過度依賴",
          "先保護我",
          "對它焦慮",
          "需電池維護"
        ],
        "itch": "帶著我的狗去任何地方，做任何事。"
      },
      {
        "name": "偵察衛星",
        "type": "Drones",
        "ability_tags": [
          "空中監視",
          "政府衛星駭客",
          "軌道激光平台",
          "寬頻感測器",
          "危險逼近警告",
          "實時小地圖",
          "目標遺忘",
          "硬光全息投影",
          "領先一步"
        ],
        "weakness_tags": [
          "不該知道的秘密",
          "政府重新指派",
          "只能使用戶外影像",
          "注意力分散"
        ],
        "itch": "遠距監視。"
      },
      {
        "name": "探測蜂群",
        "type": "Drones",
        "ability_tags": [
          "搜索危險地點",
          "測量者",
          "多枚飛行投射物",
          "追蹤目標",
          "困擾敵人",
          "協同提升",
          "視野分散",
          "融合為一",
          "以數量保險"
        ],
        "weakness_tags": [
          "焦慮牧羊人",
          "距離過遠",
          "注意力分散",
          "電量不足"
        ],
        "itch": "探查每個角落。"
      },
      {
        "name": "抗奈米裝備",
        "type": "CuttingEdge",
        "ability_tags": [
          "奈米收容",
          "奈米訊號控制",
          "煎炸式脈衝",
          "強力磁場屏障",
          "化學反應抑制噴霧",
          "整合式分子掃描器",
          "奈米科技",
          "奈米部隊戰士",
          "防化套裝"
        ],
        "weakness_tags": [
          "昂貴稀有零件",
          "遺漏破口",
          "細胞衰退",
          "政府制裁奈米"
        ],
        "itch": "清除所有微觀威脅。"
      },
      {
        "name": "擴增實境玩家",
        "type": "Cyberspace",
        "ability_tags": [
          "人生即遊戲化",
          "交錯實境戰鬥",
          "敵人掃描無人機",
          "預測性瞄準系統",
          "交錯實境力場",
          "切換外觀與道具",
          "持久作戰",
          "觀眾打賞補給",
          "耀眼的AR冠軍"
        ],
        "weakness_tags": [
          "現實太真實",
          "目標鎖定過頭",
          "公眾壓力",
          "其他玩家"
        ],
        "itch": "拿最高分！"
      },
      {
        "name": "公事包武器",
        "type": "CuttingEdge",
        "ability_tags": [
          "偽裝成日常物件",
          "以包殼猛擊",
          "長距離粒子束",
          "強化外殼",
          "任意角度射擊",
          "敵人掃描",
          "低調",
          "間諜增幅",
          "普通西裝外表"
        ],
        "weakness_tags": [
          "沉重電池",
          "需全神貫注操作",
          "過度自信",
          "力場干擾"
        ],
        "itch": "用我的祕密讓他們大吃一驚。"
      },
      {
        "name": "強化複製人",
        "type": "Augmentation",
        "ability_tags": [
          "完美的身體狀態",
          "極致的身體控制",
          "閃電般反應",
          "長相與原主無異",
          "進入休眠狀態",
          "精心構建的人格",
          "生命系統備份",
          "超人體能",
          "人格切換"
        ],
        "weakness_tags": [
          "仰賴昂貴藥物",
          "突發閃回",
          "情感表現受限",
          "因為「更優秀」而被仇恨"
        ],
        "itch": "在每方面都超越原主。"
      },
      {
        "name": "引人注目的投影",
        "type": "Augmentation",
        "ability_tags": [
          "創造繽紛影像",
          "全像偽裝",
          "混淆視覺",
          "致盲光束",
          "製造混亂",
          "空間感知",
          "3D 全像攝影機",
          "吸引目光專家",
          "無法忽視"
        ],
        "weakness_tags": [
          "分不清真實與幻象",
          "自我目眩",
          "怕曬",
          "看起來像企業的工具人"
        ],
        "itch": "吸引所有人的注意，操弄他們的情緒。"
      },
      {
        "name": "巨型戰鬥機甲",
        "type": "Drones",
        "ability_tags": [
          "踐踏與猛擊",
          "超大型機甲駕駛",
          "核心能源武裝",
          "半自動運作",
          "厚甲",
          "跳躍增幅",
          "主動偽裝系統",
          "平凡交通模式",
          "凌駕對手"
        ],
        "weakness_tags": [
          "過度嗜戰",
          "體積龐大",
          "駕駛艙視野受限",
          "稀有零件難找"
        ],
        "itch": "別讓任何東西擋住我的去路。"
      },
      {
        "name": "全像夥伴",
        "type": "Drones",
        "ability_tags": [
          "協助我的工作",
          "人工智慧編程",
          "誘人的干擾",
          "通曉各種語言",
          "防駭入能力",
          "投影多重影像",
          "隱形能力",
          "模仿他人",
          "善於交際"
        ],
        "weakness_tags": [
          "個性尚未穩定",
          "什麼都要插嘴",
          "會被忘記它不是實體",
          "運行於特定域名"
        ],
        "itch": "把我的全像夥伴當作真人一樣對待。"
      },
      {
        "name": "蜘蛛駕駛",
        "type": "Drones",
        "ability_tags": [
          "爬牆爪",
          "機甲跑酷",
          "隱藏武器",
          "熱能追蹤",
          "強化機體",
          "承載重物",
          "以天候為掩護",
          "偽裝成工業機具",
          "勝者心態"
        ],
        "weakness_tags": [
          "冒險成癮",
          "突如其來的震動",
          "干擾極強",
          "機體易損"
        ],
        "itch": "在摩天大樓邊緣追求刺激與速度。"
      },
      {
        "name": "鐳射刀",
        "type": "CuttingEdge",
        "ability_tags": [
          "切開幾乎任何東西",
          "偏轉能量",
          "瞬間斷肢",
          "破壞障礙",
          "噴射雷射片",
          "敵弱點掃描",
          "劍術訓練",
          "私人訂製武器",
          "反光戰衣"
        ],
        "weakness_tags": [
          "笨重電池",
          "容易自殘",
          "執著於這把刀",
          "鏡面防禦系統"
        ],
        "itch": "切開一切。"
      },
      {
        "name": "陽犬套裝",
        "type": "CuttingEdge",
        "ability_tags": [
          "雷射步槍",
          "強力電池",
          "耐熱與防護",
          "電力工程",
          "聚焦日光轟炸",
          "太陽劍衛軍官",
          "耐用材質",
          "吸收太陽能",
          "彈道插板"
        ],
        "weakness_tags": [
          "笨重電池",
          "難以降溫",
          "高壓電流",
          "過載破壞"
        ],
        "itch": "供電給整個城市網絡。"
      },
      {
        "name": "合成身體",
        "type": "CuttingEdge",
        "ability_tags": [
          "承受重擊",
          "為其他設備供能",
          "隱藏武器護套",
          "自我修復套件",
          "肢體脫離",
          "精密醫療掃描",
          "機械工程學",
          "專屬賽博實驗室通道",
          "工具接點"
        ],
        "weakness_tags": [
          "電量低",
          "拾荒者與敵對機械師",
          "動作遲緩",
          "與靈性斷絕"
        ],
        "itch": "成為完全自給自足的存在。"
      },
      {
        "name": "玉手箱駭客",
        "type": "Cyberspace",
        "ability_tags": [
          "玉手箱大收藏",
          "依任務客製主機",
          "專屬硬體加速器",
          "\"鑽機\"防火牆突破盒",
          "\"犀牛\"強化化身盒",
          "\"SPD3READ\"快搜模組",
          "\"鏡像\"分身模組",
          "\"假印章\"偽造器",
          "壓倒對手"
        ],
        "weakness_tags": [
          "纏繞的線與盒",
          "死板不靈活",
          "準備不足",
          "迅速進化的數位體"
        ],
        "itch": "找到每種挑戰對應的玉手箱。"
      }
    ]
  }
}
